NetkillerBlockchain/README.md
NetkillerBlockchain/__init__.py
NetkillerBlockchain/__main__.py
NetkillerBlockchain/file.epub
NetkillerBlockchain/index.html
NetkillerBlockchain/css/__init__.py
NetkillerBlockchain/css/annotations.css
NetkillerBlockchain/css/main.css
NetkillerBlockchain/css/normalize.css
NetkillerBlockchain/css/popup.css
NetkillerBlockchain/font/__init__.py
NetkillerBlockchain/font/fontello.eot
NetkillerBlockchain/font/fontello.svg
NetkillerBlockchain/font/fontello.ttf
NetkillerBlockchain/font/fontello.woff
NetkillerBlockchain/img/__init__.py
NetkillerBlockchain/img/annotator-glyph-sprite.png
NetkillerBlockchain/img/annotator-icon-sprite.png
NetkillerBlockchain/img/apple-touch-icon.png
NetkillerBlockchain/img/cancelfullscreen.png
NetkillerBlockchain/img/close.png
NetkillerBlockchain/img/fullscreen.png
NetkillerBlockchain/img/loader.gif
NetkillerBlockchain/img/menu-icon.png
NetkillerBlockchain/img/save.png
NetkillerBlockchain/img/saved.png
NetkillerBlockchain/img/settings-s.png
NetkillerBlockchain/img/settings.png
NetkillerBlockchain/img/star.png
NetkillerBlockchain/js/__init__.py
NetkillerBlockchain/js/epub.js
NetkillerBlockchain/js/epub.min.js
NetkillerBlockchain/js/epub.min.map
NetkillerBlockchain/js/hooks.min.js
NetkillerBlockchain/js/hooks.min.map
NetkillerBlockchain/js/reader.js
NetkillerBlockchain/js/reader.js.map
NetkillerBlockchain/js/reader.min.js
NetkillerBlockchain/js/reader.min.map
NetkillerBlockchain/js/hooks/__init__.py
NetkillerBlockchain/js/hooks/extensions/__init__.py
NetkillerBlockchain/js/hooks/extensions/highlight.js
NetkillerBlockchain/js/libs/__init__.py
NetkillerBlockchain/js/libs/jquery.min.js
NetkillerBlockchain/js/libs/localforage.min.js
NetkillerBlockchain/js/libs/screenfull.js
NetkillerBlockchain/js/libs/screenfull.min.js
NetkillerBlockchain/js/libs/zip.min.js
NetkillerBlockchain/js/plugins/__init__.py
NetkillerBlockchain/js/plugins/hypothesis.js
NetkillerBlockchain/js/plugins/search.js
netkiller_blockchain-2024.3.5.0.dist-info/METADATA
netkiller_blockchain-2024.3.5.0.dist-info/WHEEL
netkiller_blockchain-2024.3.5.0.dist-info/entry_points.txt
netkiller_blockchain-2024.3.5.0.dist-info/top_level.txt
netkiller_blockchain-2024.3.5.0.dist-info/RECORD
